me_finder/__init__.py
me_finder/cli.py
me_finder/config.ini
me_finder/context.py
me_finder/converters.py
me_finder/errors.py
me_finder/io.py
me_finder/logging.yml
me_finder/prediction.py
me_finder/result.py
me_finder/shell.py
me_finder/version.py
me_finder/predictor/__init__.py
me_finder/predictor/detect.py
me_finder/predictor/parse.py
me_finder/predictor/putative.py
me_finder/predictor/types.py
me_finder/tools/__init__.py
me_finder/tools/blast.py
me_finder/tools/hmmer.py
me_finder/tools/kma.py
MobileElementFinder-1.1.2.dist-info/LICENSE
MobileElementFinder-1.1.2.dist-info/METADATA
MobileElementFinder-1.1.2.dist-info/WHEEL
MobileElementFinder-1.1.2.dist-info/entry_points.txt
MobileElementFinder-1.1.2.dist-info/top_level.txt
MobileElementFinder-1.1.2.dist-info/RECORD
