Metadata-Version: 2.1
Name: MobileElementFinder
Version: 1.1.2
Summary: Mobile Genetic Element prediction
Home-page: https://bitbucket.org/mhkj/mge_finder/src/master/
Author: Markus Johansson
Author-email: markjo@food.dtu.dk
License: GPLv3
Platform: UNKNOWN
Classifier: License :: OSI Approved :: GNU General Public License v3 (GPLv3)
Classifier: Programming Language :: Python :: 3.6
Classifier: Programming Language :: Python :: 3.7
Classifier: Programming Language :: Python :: 3.8
Requires-Python: >=3.7
License-File: LICENSE
Requires-Dist: Click
Requires-Dist: MGEdb (==1.1.1)
Requires-Dist: PyYAML
Requires-Dist: attrs
Requires-Dist: biopython (<=1.80)
Requires-Dist: bcbio-gff
Requires-Dist: cattrs
Requires-Dist: mypy
Requires-Dist: tabulate
Provides-Extra: test
Requires-Dist: ipdb ; extra == 'test'
Requires-Dist: pytest ; extra == 'test'
Requires-Dist: pytest-runner ; extra == 'test'
Requires-Dist: pytest-cov ; extra == 'test'
